pyecharts_extras/__init__.py
pyecharts_extras/_version.py
pyecharts_extras/choropleth_map.py
pyecharts_extras/date_time.py
pyecharts_extras-0.0.5.dist-info/METADATA
pyecharts_extras-0.0.5.dist-info/WHEEL
pyecharts_extras-0.0.5.dist-info/top_level.txt
pyecharts_extras-0.0.5.dist-info/RECORD
