Metadata-Version: 2.1
Name: pyecharts-extras
Version: 0.0.5
Summary: Draw speciaized graphs using pyecharts
Home-page: https://github.com/pyecharts/pyecharts-extras
Author: pyecharts dev team
Author-email: info@pyecharts.com
License: MIT
Download-URL: https://github.com/pyecharts/pyecharts-extras/archive/0.0.5.tar.gz
Keywords: python,pyecharts,chart
Platform: UNKNOWN
Classifier: Topic :: Software Development :: Libraries
Classifier: Programming Language :: Python
Classifier: Intended Audience :: Developers
Classifier: Programming Language :: Python :: 2.6
Classifier: Programming Language :: Python :: 2.7
Classifier: Programming Language :: Python :: 3.3
Classifier: Programming Language :: Python :: 3.4
Classifier: Programming Language :: Python :: 3.5
Classifier: Programming Language :: Python :: 3.6
Classifier: Programming Language :: Python :: 3.7
Classifier: Programming Language :: Python :: 3.8
Requires-Dist: pyecharts (>=1.3.1)
